pymake/__init__.py
pymake/cli.py
pymake/core.py
pymake/executor.py
pymake/utils.py
pymakex-0.1.0.dist-info/licenses/LICENSE
pymakex-0.1.0.dist-info/METADATA
pymakex-0.1.0.dist-info/WHEEL
pymakex-0.1.0.dist-info/entry_points.txt
pymakex-0.1.0.dist-info/top_level.txt
pymakex-0.1.0.dist-info/RECORD
